scavengr/__init__.py
scavengr/__main__.py
scavengr/_version.py
scavengr/cli.py
scavengr/application/__init__.py
scavengr/application/dictionary.py
scavengr/application/extract.py
scavengr/application/validate.py
scavengr/config/__init__.py
scavengr/config/config_manager.py
scavengr/config/env_config.py
scavengr/core/__init__.py
scavengr/core/entities.py
scavengr/core/interfaces.py
scavengr/core/services.py
scavengr/infrastructure/__init__.py
scavengr/infrastructure/database/__init__.py
scavengr/infrastructure/database/base_scanner.py
scavengr/infrastructure/database/connector.py
scavengr/infrastructure/database/scanners.py
scavengr/infrastructure/exporters/__init__.py
scavengr/infrastructure/exporters/output_writer.py
scavengr/infrastructure/formatters/__init__.py
scavengr/infrastructure/formatters/dbml_formatter.py
scavengr/infrastructure/parsers/__init__.py
scavengr/infrastructure/parsers/dbml_parser.py
scavengr/utils/README.md
scavengr/utils/__init__.py
scavengr/utils/constants.py
scavengr/utils/exceptions.py
scavengr/utils/logging_config.py
scavengr/utils/ui_helpers.py
scavengr/utils/validators.py
scavengr-0.0.2.dist-info/licenses/LICENSE
scavengr-0.0.2.dist-info/METADATA
scavengr-0.0.2.dist-info/WHEEL
scavengr-0.0.2.dist-info/entry_points.txt
scavengr-0.0.2.dist-info/top_level.txt
scavengr-0.0.2.dist-info/RECORD
