Metadata-Version: 2.4
Name: scavengr
Version: 0.0.2
Summary: Scavengr — Recolector y documentador de metadatos en bases de datos
Author-email: Json Rivera <jsonrivera@proton.me>
Maintainer-email: Json Rivera <jsonrivera@proton.me>
License-Expression: MIT
Project-URL: Homepage, https://github.com/JasRockr/Scavengr
Project-URL: Repository, https://github.com/JasRockr/Scavengr.git
Project-URL: Issues, https://github.com/JasRockr/Scavengr/issues
Project-URL: Documentation, https://github.com/JasRockr/Scavengr#readme
Keywords: database,dbml,metadata,documentation,schema,data-dictionary,clean-architecture,cli,tool,scavengr
Classifier: Development Status :: 3 - Alpha
Classifier: Intended Audience :: Developers
Classifier: Intended Audience :: System Administrators
Classifier: Topic :: Database :: Database Engines/Servers
Classifier: Topic :: Software Development :: Documentation
Classifier: Topic :: System :: Systems Administration
Classifier: Programming Language :: Python :: 3
Classifier: Programming Language :: Python :: 3.8
Classifier: Programming Language :: Python :: 3.9
Classifier: Programming Language :: Python :: 3.10
Classifier: Programming Language :: Python :: 3.11
Classifier: Programming Language :: Python :: 3.12
Classifier: Operating System :: OS Independent
Requires-Python: >=3.8
License-File: LICENSE
Requires-Dist: python-dotenv==1.1
Requires-Dist: openpyxl==3.1
Provides-Extra: postgres
Requires-Dist: psycopg2-binary>=2.9; extra == "postgres"
Provides-Extra: mysql
Requires-Dist: PyMySQL>=1.0; extra == "mysql"
Requires-Dist: mysql-connector-python>=8.0; extra == "mysql"
Provides-Extra: mssql
Requires-Dist: pyodbc>=4.0; extra == "mssql"
Provides-Extra: all-db
Requires-Dist: psycopg2-binary>=2.9; extra == "all-db"
Requires-Dist: PyMySQL>=1.0; extra == "all-db"
Requires-Dist: mysql-connector-python>=8.0; extra == "all-db"
Requires-Dist: pyodbc>=4.0; extra == "all-db"
Provides-Extra: dev
Requires-Dist: pytest>=7.0; extra == "dev"
Requires-Dist: pytest-cov>=2.0; extra == "dev"
Requires-Dist: flake8>=3.8; extra == "dev"
Requires-Dist: black>=21.0; extra == "dev"
Requires-Dist: isort>=5.0; extra == "dev"
Requires-Dist: mypy; extra == "dev"
Requires-Dist: pre-commit; extra == "dev"
Requires-Dist: safety; extra == "dev"
Requires-Dist: bandit; extra == "dev"
Dynamic: license-file
